cubamap/__init__.py
cubamap/frontend/build/asset-manifest.json
cubamap/frontend/build/index.html
cubamap/frontend/build/precache-manifest.dbd5f4f102137286b34e2c1847566088.js
cubamap/frontend/build/service-worker.js
cubamap/frontend/build/static/css/2.38ca0958.chunk.css
cubamap/frontend/build/static/css/2.38ca0958.chunk.css.map
cubamap/frontend/build/static/js/2.5dc22b8d.chunk.js
cubamap/frontend/build/static/js/2.5dc22b8d.chunk.js.LICENSE.txt
cubamap/frontend/build/static/js/2.5dc22b8d.chunk.js.map
cubamap/frontend/build/static/js/main.33a19cc2.chunk.js
cubamap/frontend/build/static/js/main.33a19cc2.chunk.js.LICENSE.txt
cubamap/frontend/build/static/js/main.33a19cc2.chunk.js.map
cubamap/frontend/build/static/js/runtime-main.11ec9aca.js
cubamap/frontend/build/static/js/runtime-main.11ec9aca.js.map
cubamap-0.0.1.dist-info/LICENSE
cubamap-0.0.1.dist-info/METADATA
cubamap-0.0.1.dist-info/WHEEL
cubamap-0.0.1.dist-info/top_level.txt
cubamap-0.0.1.dist-info/RECORD
