Metadata-Version: 2.1
Name: cubamap
Version: 0.0.1
Summary: A streamlit component to 
Home-page: UNKNOWN
Author: hiancd
Author-email: hiancdtrsnm@gmail.com
License: UNKNOWN
Platform: UNKNOWN
Requires-Python: >=3.6
Requires-Dist: streamlit (>=0.63)
